{
  "timestamp": "2025-11-20 07:48:20",
  "requested_size_min": 60,
  "requested_size_max": 150,
  "total_posts": 761,
  "valid_for_averages": 733,
  "overall_avg_price_per_sqm": 201830832,
  "age_intervals": {
    "0-4": {
      "avg": 224261648,
      "count": 279
    },
    "5-9": {
      "avg": 194939814,
      "count": 216
    },
    "10-14": {
      "avg": 187661016,
      "count": 177
    },
    "15-20": {
      "avg": 164754098,
      "count": 61
    }
  },
  "size_intervals": {
    "<80": {
      "avg": 202348101,
      "count": 158
    },
    "80-120": {
      "avg": 199103671,
      "count": 463
    },
    ">120": {
      "avg": 212375000,
      "count": 112
    }
  },
  "age_size_matrix": {
    "0-4": {
      "<80": {
        "avg": 223717391,
        "count": 46
      },
      "80-120": {
        "avg": 221560439,
        "count": 182
      },
      ">120": {
        "avg": 234392156,
        "count": 51
      }
    },
    "5-9": {
      "<80": {
        "avg": 199111111,
        "count": 45
      },
      "80-120": {
        "avg": 191402777,
        "count": 144
      },
      ">120": {
        "avg": 206851851,
        "count": 27
      }
    },
    "10-14": {
      "<80": {
        "avg": 190177419,
        "count": 62
      },
      "80-120": {
        "avg": 184494845,
        "count": 97
      },
      ">120": {
        "avg": 196055555,
        "count": 18
      }
    },
    "15-20": {
      "<80": {
        "avg": 185800000,
        "count": 5
      },
      "80-120": {
        "avg": 160075000,
        "count": 40
      },
      ">120": {
        "avg": 169875000,
        "count": 16
      }
    }
  }
}